play_store.py
play_store-1.0.dist-info/METADATA
play_store-1.0.dist-info/WHEEL
play_store-1.0.dist-info/top_level.txt
play_store-1.0.dist-info/RECORD
