Metadata-Version: 2.1
Name: play-store
Version: 1.0
Summary: Scrapes data from Google Play Store
Home-page: https://github.com/WoolDoughnut310/google-play
Author: J. Nma
Author-email: wooldoughnutspi@outlook.com
License: UNKNOWN
Keywords: python3 web-scraping google-play data applications
Platform: UNKNOWN
Classifier: Development Status :: 5 - Production/Stable
Classifier: Intended Audience :: Developers
Classifier: License :: OSI Approved :: MIT License
Classifier: Topic :: Software Development :: Libraries
Classifier: Programming Language :: Python :: 3
Requires-Python: >=3
